{
  "lastUsed": 4,
  "questions": [
    {
      "options": [
        "不跑",
        "一公里",
        "三公里",
        "五公里",
        "十公里"
      ],
      "title": "🏃  跑步"
    },
    {
      "options": [
        "大冒险",
        "真心话",
        "Pass"
      ],
      "title": "🍺  大冒险&真心话"
    },
    {
      "options": [
        "1",
        "2",
        "3",
        "4",
        "5",
        "6"
      ],
      "title": "🎲  投掷骰子"
    },
    {
      "options": [
        "玩游戏",
        "看电影",
        "跑步",
        "爬山"
      ],
      "title": "🍸  明天干什么"
    },
    {
      "options": [
        "火锅",
        "自助",
        "烤鱼",
        "海鲜",
        "海底捞",
        "外婆家",
        "日本料理",
        "烧烤",
        "大米饭盖饭",
        "麻辣烫"
      ],
      "title": "🍲  聚餐吃什么"
    }
  ]
}